crawlerpy/__init__.py
crawlerpy/dtc.py
crawlerpy/sap.py
crawlerpy/scmb.py
crawlerpy/util.py
crawlerpy/vdm.py
crawler_py-2.0.8.dist-info/LICENSE
crawler_py-2.0.8.dist-info/METADATA
crawler_py-2.0.8.dist-info/WHEEL
crawler_py-2.0.8.dist-info/top_level.txt
crawler_py-2.0.8.dist-info/RECORD
