Metadata-Version: 2.1
Name: crawler-py
Version: 2.0.8
Summary: A web Crawler for DTC(dans ton chat), VDM(vie de merde) and SCMB(se coucher moins bete)
Home-page: http://johann-lecocq.fr/informatique-detail---bibliotheque--crawlerpy.html
Author: Johann Lecocq
Author-email: git-jo@johann-lecocq.fr
License: GNU GPL 2
Platform: any
Classifier: Operating System :: OS Independent
Classifier: Programming Language :: Python
Classifier: Programming Language :: Python :: 3
Classifier: Natural Language :: French
Classifier: License :: OSI Approved :: GNU General Public License v2 (GPLv2)
License-File: LICENSE
Requires-Dist: beautifulsoup4 ==4.12.3
Requires-Dist: requests ==2.32.3
